{
    "created_time": "2023-05-04T00:20:01Z",
    "files": [
        {
            "attachment_folder": "",
            "created_time": "2023-05-04T00:21:36Z",
            "id": "121",
            "modified_time": "2023-05-04T08:32:42Z",
            "name": "公用组件模型.md",
            "signature": "784285914973272720",
            "tags": [
            ]
        },
        {
            "attachment_folder": "",
            "created_time": "2023-05-04T01:35:48Z",
            "id": "122",
            "modified_time": "2023-05-04T02:20:05Z",
            "name": "基础设施监控视图.md",
            "signature": "5546498803274812404",
            "tags": [
            ]
        },
        {
            "attachment_folder": "",
            "created_time": "2023-05-04T02:21:17Z",
            "id": "123",
            "modified_time": "2023-05-04T07:14:29Z",
            "name": "云原生.md",
            "signature": "8223662518574454429",
            "tags": [
            ]
        }
    ],
    "folders": [
    ],
    "id": "120",
    "modified_time": "2023-05-04T00:20:01Z",
    "signature": "207324049504817",
    "version": 3
}
